gwcert/__init__.py
gwcert/__main__.py
gwcert/ca/__init__.py
gwcert/ca/__main__.py
gwcert/key/__init__.py
gwcert/key/__main__.py
gwcert/paths.py
gwcert/py.typed
gridworks_cert-0.5.0.dist-info/LICENSE
gridworks_cert-0.5.0.dist-info/METADATA
gridworks_cert-0.5.0.dist-info/WHEEL
gridworks_cert-0.5.0.dist-info/entry_points.txt
gridworks_cert-0.5.0.dist-info/RECORD
