Metadata-Version: 2.1
Name: gridworks-cert
Version: 0.5.0
Summary: TLS certificate management tools for GridWorks
Home-page: https://github.com/thegridelectric/gridworks-cert
License: MIT
Author: Andrew Schweitzer
Author-email: schweitz72@gmail.com
Requires-Python: >=3.10,<4.0
Classifier: Development Status :: 3 - Alpha
Classifier: License :: OSI Approved :: MIT License
Classifier: Programming Language :: Python :: 3
Classifier: Programming Language :: Python :: 3.10
Classifier: Programming Language :: Python :: 3.11
Classifier: Programming Language :: Python :: 3.12
Requires-Dist: click (<8.2)
Requires-Dist: ownca (>=0.4.0)
Requires-Dist: rich (>=12.0.0)
Requires-Dist: trogon (>=0.5.0)
Requires-Dist: typer (>=0.16.0)
Requires-Dist: xdg (>=6.0.0)
Project-URL: Changelog, https://github.com/thegridelectric/gridworks-cert/releases
Project-URL: Documentation, https://gridworks-cert.readthedocs.io
Project-URL: Repository, https://github.com/thegridelectric/gridworks-cert
